openai_manager/__init__.py
openai_manager/api_resources.py
openai_manager/auth_manager.py
openai_manager/exceptions.py
openai_manager/producer_consumer.py
openai_manager/serving.py
openai_manager/utils.py
tests/test_serving.py
tests/test_sync_create.py
openai_manager-1.0.0.dist-info/METADATA
openai_manager-1.0.0.dist-info/WHEEL
openai_manager-1.0.0.dist-info/top_level.txt
openai_manager-1.0.0.dist-info/RECORD
