Metadata-Version: 2.1
Name: openai-manager
Version: 1.0.0
Summary: Speed up your OpenAI requests by balancing prompts to multiple API keys.
Home-page: https://github.com/MrZilinXiao/openai-manager
Author: MrZilinXiao
Author-email: me@mrxiao.net
License: MIT
Classifier: Programming Language :: Python :: 3
Classifier: License :: OSI Approved :: MIT License
Classifier: Operating System :: OS Independent
Requires-Python: >=3.7
Requires-Dist: aiohttp
Requires-Dist: openai
Requires-Dist: tiktoken
Requires-Dist: fastapi
